<?xml version="1.0" encoding="utf-8"?>
<content>
  <file_system name="Safety" id="Safety~0000" />
  <file name="StorageProperties.xml" id="StorageProperties~0000.xml" />
  <file name="StorageContent.xml" id="StorageContent~0000.xml" />
  <folder name="PROJECT">
    <file name="PROJECT.proj" id="PROJECT~PROJECT~0000.proj" />
    <folder name="AspectHierarchies">
      <file name="LinkRepository.xml" id="AspectHie~LinkReposi~0000.xml" />
    </folder>
    <folder name="Hardware">
      <file name="029ff071-2629-4cc8-8ae1-9c32f44586a4.DataLink" id="Hardware~029ff071-26~0000.DataLink" />
      <file name="029ff071-2629-4cc8-8ae1-9c32f44586a4.projset" id="Hardware~029ff071-26~0001.projset" />
      <file name="029ff071-2629-4cc8-8ae1-9c32f44586a4.Transport" id="Hardware~029ff071-26~0002.Transport" />
      <file name="VersionHistory.usermeta" id="Hardware~VersionHist~0000.usermeta" />
      <file name="Description.html" id="Hardware~Description~0000.html" />
      <folder name="CFG_13E86C9EF2F047EF8CCCE6D7644CFEAE">
        <file name="d24d551d-4eb0-4b0b-af1c-884cda8336da.ds" id="CFG_13E86~d24d551d-4~0000.ds" />
        <file name="DataList.dl" id="CFG_13E86C9~DataList~0000.dl" />
        <file name="PlmConfiguration.plmc" id="CFG_13E86~PlmConfigu~0000.plmc" />
        <folder name="AXLF_Master">
          <file name="Arp.Io.Axl.ControllerComponent.compmeta" id="AXLF_Mast~Arp.Io.Axl~0000.compmeta" />
          <file name="Arp.Io.Axl.libmeta" id="AXLF_Mast~Arp.Io.Axl~0001.libmeta" />
        </folder>
        <folder name="HMI_Server">
          <file name="Arp.Plc.Ehmi.libmeta" id="HMI_Serve~Arp.Plc.Eh~0000.libmeta" />
          <file name="DataList.dlr4hmi" id="HMI_Server~DataList~0000.dlr4hmi" />
          <file name="EhmiComponent.compmeta" id="HMI_Serve~EhmiCompon~0000.compmeta" />
          <file name="HmiConfiguration.xml" id="HMI_Serve~HmiConfigu~0000.xml" />
          <folder name="Application">
            <file name="Navigation.hminav" id="Applicati~Navigation~0000.hminav" />
            <file name="Profiles.hmiprofiles" id="Application~Profiles~0000.hmiprofiles" />
            <file name="Variables.hmivar" id="Applicatio~Variables~0000.hmivar" />
            <folder name="Login.hmi">
              <file name="Definition.hmipagedef" id="Login.hmi~Definition~0002.hmipagedef" />
              <file name="Definition.hmipagedef.locres" id="Login.hmi~Definition~0003.locres" />
              <file name="Parameters.hmiparams" id="Login.hmi~Parameters~0001.hmiparams" />
              <file name="Variables.hmivar" id="Login.hmi~Variables~0000.hmivar" />
            </folder>
            <folder name="Page.hmi">
              <file name="Definition.hmipagedef" id="Page.hmi~Definition~0000.hmipagedef" />
              <file name="Definition.hmipagedef.locres" id="Page.hmi~Definition.~0000.locres" />
              <file name="Parameters.hmiparams" id="Page.hmi~Parameters~0000.hmiparams" />
              <file name="Variables.hmivar" id="Page.hmi~Variables~0000.hmivar" />
            </folder>
          </folder>
        </folder>
        <folder name="IB_Master">
          <file name="Arp.Io.Ib.ControllerComponent.compmeta" id="IB_Master~Arp.Io.Ib.~0000.compmeta" />
          <file name="Arp.Io.Ib.libmeta" id="IB_Master~Arp.Io.Ib~0000.libmeta" />
        </folder>
        <folder name="PLCnext">
          <file name="EsmConfiguration.esmc" id="PLCnext~EsmConfigura~0000.esmc" />
        </folder>
        <folder name="PN_Master">
          <file name="Arp.Io.Pn.libmeta" id="PN_Master~Arp.Io.Pn~0000.libmeta" />
          <file name="ControllerComponent.compmeta" id="PN_Master~Controller~0000.compmeta" />
        </folder>
        <folder name="RES_D2E423A3C95340D4AD848909D059FEAD">
          <file name="Arp.Plc.Eclr.libmeta" id="RES_D2E42~Arp.Plc.Ec~0000.libmeta" />
          <file name="DataList.dlr4var" id="RES_D2E423A~DataList~0000.dlr4var" />
          <file name="EclrComponent.compmeta" id="RES_D2E42~EclrCompon~0000.compmeta" />
          <file name="GlobalVariables.var" id="RES_D2E42~GlobalVari~0000.var" />
          <file name="IOConfiguration.ioc" id="RES_D2E42~IOConfigur~0000.ioc" />
          <file name="ResourceSettings.set" id="RES_D2E42~ResourceSe~0000.set" />
        </folder>
      </folder>
    </folder>
    <folder name="Logical Elements">
      <file name="DefaultBlankPage.hmipagetemplate" id="Logical E~DefaultBla~0000.hmipagetemplate" />
      <file name="GeneratedDataTypes.dt" id="Logical E~GeneratedD~0000.dt" />
      <folder name="Login.hmipagetemplate">
        <file name="Definition.hmipagedef" id="Login.hmi~Definition~0000.hmipagedef" />
        <file name="Definition.hmipagedef.locres" id="Login.hmi~Definition~0001.locres" />
        <file name="Parameters.hmiparams" id="Login.hmi~Parameters~0000.hmiparams" />
        <file name="Variables.hmivar" id="Login.hmip~Variables~0000.hmivar" />
      </folder>
      <folder name="Main.pou">
        <file name="Code.ld" id="Main.pou~Code~0000.ld" />
        <file name="Code.ld.locres" id="Main.pou~Code.ld~0000.locres" />
        <file name="Metadata.meta" id="Main.pou~Metadata~0000.meta" />
        <file name="User.locres" id="Main.pou~User~0000.locres" />
        <file name="Variables.var" id="Main.pou~Variables~0000.var" />
        <file name="Variables.var.locres" id="Main.pou~Variables.v~0000.locres" />
      </folder>
      <folder name="sql_analytics.jpg">
        <file name="Source" id="sql_analytics~Source~0000" />
        <file name="Thumbnail" id="sql_analyt~Thumbnail~0000" />
      </folder>
      <folder name="sql_api.png">
        <file name="Source" id="sql_api.png~Source~0000" />
        <file name="Thumbnail" id="sql_api.pn~Thumbnail~0000" />
      </folder>
      <folder name="sql_bulk.png">
        <file name="Source" id="sql_bulk.png~Source~0000" />
        <file name="Thumbnail" id="sql_bulk.p~Thumbnail~0000" />
      </folder>
      <folder name="sql_database.jpg">
        <file name="Source" id="sql_database.~Source~0000" />
        <file name="Thumbnail" id="sql_databa~Thumbnail~0000" />
      </folder>
      <folder name="HMILogic.pou">
        <file name="User.locres" id="HMILogic.pou~User~0000.locres" />
        <file name="Code.st" id="HMILogic.pou~Code~0000.st" />
        <file name="Variables.var.locres" id="HMILogic.~Variables.~0000.locres" />
        <file name="Metadata.meta" id="HMILogic.po~Metadata~0000.meta" />
        <file name="Variables.var" id="HMILogic.p~Variables~0000.var" />
        <file name="VersionHistory.usermeta" id="HMILogic.~VersionHis~0000.usermeta" />
        <file name="Description.html" id="HMILogic.~Descriptio~0000.html" />
        <file name="Description.rtf" id="HMILogic.~Descriptio~0001.rtf" />
      </folder>
    </folder>
    <folder name="RecycleBin">
      <folder name="714f5443-a142-41ac-8c50-c23d736437ae">
        <file name="714f5443-a142-41ac-8c50-c23d736437ae" id="714f5443-~714f5443-a~0000" />
        <folder name="sql_analytics1.jpg">
          <file name="Source" id="sql_analytics~Source~0001" />
          <file name="Thumbnail" id="sql_analyt~Thumbnail~0001" />
        </folder>
      </folder>
    </folder>
  </folder>
</content>